calculadora_codaqui/__init__.py
calculadora_codaqui/__main__.py
calculadora_codaqui/soma.py
calculadora_codaqui-0.0.2.dist-info/WHEEL
calculadora_codaqui-0.0.2.dist-info/METADATA
calculadora_codaqui-0.0.2.dist-info/RECORD
